{"v":"4.8.0","meta":{"g":"LottieFiles AE 3.1.1","a":"","k":"","d":"","tc":""},"fr":60,"ip":0,"op":78,"w":96,"h":76,"nm":"Logo Animation - App Loader WHITE 2","ddd":0,"assets":[{"id":"comp_0","layers":[{"ddd":0,"ind":1,"ty":3,"nm":"NULL 2","sr":1,"ks":{"o":{"a":0,"k":0,"ix":11},"r":{"a":0,"k":0,"ix":10},"p":{"a":0,"k":[47.5,54.5,0],"ix":2},"a":{"a":0,"k":[50,50,0],"ix":1},"s":{"a":0,"k":[25,25,100],"ix":6}},"ao":0,"ip":-4,"op":60,"st":14,"bm":0},{"ddd":0,"ind":2,"ty":4,"nm":"Layer 2 Outlines 4","parent":4,"sr":1,"ks":{"o":{"a":0,"k":100,"ix":11},"r":{"a":1,"k":[{"i":{"x":[0.833],"y":[0.833]},"o":{"x":[0.167],"y":[0.167]},"t":42.8,"s":[0]},{"i":{"x":[0.833],"y":[0.833]},"o":{"x":[0.167],"y":[0.167]},"t":53.001,"s":[40]},{"i":{"x":[0.833],"y":[0.833]},"o":{"x":[0.167],"y":[0.167]},"t":338.001,"s":[0]},{"i":{"x":[0.833],"y":[0.833]},"o":{"x":[0.167],"y":[0.167]},"t":342.8,"s":[-1]},{"i":{"x":[0.833],"y":[0.833]},"o":{"x":[0.167],"y":[0.167]},"t":347.6,"s":[-1]},{"t":357.2,"s":[40]}],"ix":10,"x":"var $bm_rt;\nvar enable, amp, freq, decay, n, t, v;\ntry {\n    $bm_rt = enable = effect('Excite - Rotation')('Pseudo/BNCA2506f0b33-0001');\n    if (enable == 0) {\n        $bm_rt = value;\n    } else {\n        amp = $bm_div(effect('Excite - Rotation')('Pseudo/BNCA2506f0b33-0003'), 2.5);\n        freq = $bm_div(effect('Excite - Rotation')('Pseudo/BNCA2506f0b33-0004'), 20);\n        decay = $bm_div(effect('Excite - Rotation')('Pseudo/BNCA2506f0b33-0005'), 20);\n        n = 0, 0 < numKeys && (n = nearestKey(time).index, key(n).time > time && n--), t = 0 === n ? 0 : $bm_sub(time, key(n).time), $bm_rt = 0 < n ? (v = velocityAtTime($bm_sub(key(n).time, $bm_div(thisComp.frameDuration, 10))), $bm_sum(value, $bm_div($bm_mul($bm_mul($bm_div(v, 100), amp), Math.sin($bm_mul($bm_mul($bm_mul(freq, t), 2), Math.PI))), Math.exp($bm_mul(decay, t))))) : value;\n    }\n} catch (err) {\n    $bm_rt = value = value;\n}"},"p":{"a":1,"k":[{"i":{"x":0.833,"y":0.833},"o":{"x":0.167,"y":0.167},"t":42.8,"s":[73.188,150.441,0],"to":[-2.495,1.023,0],"ti":[0,0,0]},{"i":{"x":0.833,"y":0.833},"o":{"x":0.167,"y":0.167},"t":53.001,"s":[58.215,156.578,0],"to":[0,0,0],"ti":[0,0,0]},{"i":{"x":0.833,"y":0.833},"o":{"x":0.167,"y":0.167},"t":347.6,"s":[73.188,150.441,0],"to":[0,0,0],"ti":[2.495,-1.023,0]},{"t":357.2,"s":[58.215,156.578,0]}],"ix":2},"a":{"a":1,"k":[{"i":{"x":0.833,"y":0.833},"o":{"x":0.167,"y":0.167},"t":42.8,"s":[124.156,138.64,0],"to":[0,0,0],"ti":[0,0,0]},{"t":347.600390625,"s":[124.156,138.64,0]}],"ix":1},"s":{"a":1,"k":[{"i":{"x":[0.833,0.833,0.833],"y":[0.833,0.833,0.833]},"o":{"x":[0.167,0.167,0.167],"y":[0.167,0.167,0.167]},"t":42.8,"s":[98.18,98.18,100]},{"t":347.600390625,"s":[98.18,98.18,100]}],"ix":6}},"ao":0,"ef":[{"ty":5,"nm":"Excite - Rotation","np":8,"mn":"Pseudo/BNCA2506f0b33","ix":1,"en":1,"ef":[{"ty":7,"nm":"Enable","mn":"Pseudo/BNCA2506f0b33-0001","ix":1,"v":{"a":0,"k":1,"ix":1}},{"ty":6,"nm":"Properties","mn":"Pseudo/BNCA2506f0b33-0002","ix":2,"v":0},{"ty":0,"nm":"Overshoot","mn":"Pseudo/BNCA2506f0b33-0003","ix":3,"v":{"a":0,"k":5,"ix":3,"x":"var $bm_rt;\n$bm_rt = clamp(value, 0, 100);"}},{"ty":0,"nm":"Bounce","mn":"Pseudo/BNCA2506f0b33-0004","ix":4,"v":{"a":0,"k":30,"ix":4,"x":"var $bm_rt;\n$bm_rt = clamp(value, 0, 100);"}},{"ty":0,"nm":"Friction","mn":"Pseudo/BNCA2506f0b33-0005","ix":5,"v":{"a":0,"k":100,"ix":5,"x":"var $bm_rt;\n$bm_rt = clamp(value, 0, 100);"}},{"ty":6,"nm":"","mn":"Pseudo/BNCA2506f0b33-0006","ix":6,"v":0}]}],"shapes":[{"ty":"gr","it":[{"ind":0,"ty":"sh","ix":1,"ks":{"a":0,"k":{"i":[[-24.492,-28.634],[17.06,-14.043],[24.492,28.634],[-17.06,14.043]],"o":[[24.492,28.634],[-17.06,14.043],[-24.492,-28.634],[17.06,-14.044]],"v":[[30.889,-25.427],[44.346,51.847],[-30.889,25.428],[-44.346,-51.846]],"c":true},"ix":2},"nm":"Path 1","mn":"ADBE Vector Shape - Group","hd":false},{"ty":"st","c":{"a":0,"k":[1,1,1,1],"ix":3},"o":{"a":0,"k":100,"ix":4},"w":{"a":0,"k":7.7,"ix":5},"lc":1,"lj":1,"ml":10,"bm":0,"nm":"Stroke 1","mn":"ADBE Vector Graphic - Stroke","hd":false},{"ty":"tr","p":{"a":0,"k":[80.656,85.14],"ix":2},"a":{"a":0,"k":[0,0],"ix":1},"s":{"a":0,"k":[100,100],"ix":3},"r":{"a":0,"k":0,"ix":6},"o":{"a":0,"k":100,"ix":7},"sk":{"a":0,"k":0,"ix":4},"sa":{"a":0,"k":0,"ix":5},"nm":"Transform"}],"nm":"Group 1","np":3,"cix":2,"bm":0,"ix":1,"mn":"ADBE Vector Group","hd":false}],"ip":-4,"op":60,"st":-206.8,"bm":0},{"ddd":0,"ind":3,"ty":4,"nm":"Layer 2 Outlines 3","parent":4,"td":1,"sr":1,"ks":{"o":{"a":0,"k":100,"ix":11},"r":{"a":1,"k":[{"i":{"x":[0.667],"y":[1]},"o":{"x":[0.333],"y":[0]},"t":42.8,"s":[0]},{"i":{"x":[0.833],"y":[0.833]},"o":{"x":[0.333],"y":[0]},"t":53.001,"s":[40]},{"i":{"x":[0.833],"y":[0.833]},"o":{"x":[0.167],"y":[0.167]},"t":338.001,"s":[0]},{"i":{"x":[0.833],"y":[0.833]},"o":{"x":[0.167],"y":[0.167]},"t":342.8,"s":[-1]},{"i":{"x":[0.833],"y":[0.833]},"o":{"x":[0.167],"y":[0.167]},"t":347.6,"s":[-1]},{"t":357.2,"s":[40]}],"ix":10,"x":"var $bm_rt;\nvar enable, amp, freq, decay, n, t, v;\ntry {\n    $bm_rt = enable = effect('Excite - Rotation')('Pseudo/BNCA2506f0b33-0001');\n    if (enable == 0) {\n        $bm_rt = value;\n    } else {\n        amp = $bm_div(effect('Excite - Rotation')('Pseudo/BNCA2506f0b33-0003'), 2.5);\n        freq = $bm_div(effect('Excite - Rotation')('Pseudo/BNCA2506f0b33-0004'), 20);\n        decay = $bm_div(effect('Excite - Rotation')('Pseudo/BNCA2506f0b33-0005'), 20);\n        n = 0, 0 < numKeys && (n = nearestKey(time).index, key(n).time > time && n--), t = 0 === n ? 0 : $bm_sub(time, key(n).time), $bm_rt = 0 < n ? (v = velocityAtTime($bm_sub(key(n).time, $bm_div(thisComp.frameDuration, 10))), $bm_sum(value, $bm_div($bm_mul($bm_mul($bm_div(v, 100), amp), Math.sin($bm_mul($bm_mul($bm_mul(freq, t), 2), Math.PI))), Math.exp($bm_mul(decay, t))))) : value;\n    }\n} catch (err) {\n    $bm_rt = value = value;\n}"},"p":{"a":1,"k":[{"i":{"x":0.667,"y":1},"o":{"x":0.333,"y":0},"t":42.8,"s":[73.188,150.441,0],"to":[-2.495,1.023,0],"ti":[0,0,0]},{"i":{"x":0.833,"y":0.833},"o":{"x":0.333,"y":0},"t":53.001,"s":[58.215,156.578,0],"to":[0,0,0],"ti":[0,0,0]},{"i":{"x":0.833,"y":0.833},"o":{"x":0.167,"y":0.167},"t":347.6,"s":[73.188,150.441,0],"to":[0,0,0],"ti":[2.495,-1.023,0]},{"t":357.2,"s":[58.215,156.578,0]}],"ix":2},"a":{"a":1,"k":[{"i":{"x":0.833,"y":0.833},"o":{"x":0.333,"y":0.333},"t":42.8,"s":[124.156,138.64,0],"to":[0,0,0],"ti":[0,0,0]},{"t":347.600390625,"s":[124.156,138.64,0]}],"ix":1},"s":{"a":1,"k":[{"i":{"x":[0.833,0.833,0.833],"y":[1,1,1]},"o":{"x":[0.333,0.333,0.333],"y":[0,0,0]},"t":42.8,"s":[98.18,98.18,100]},{"t":347.600390625,"s":[98.18,98.18,100]}],"ix":6}},"ao":0,"ef":[{"ty":5,"nm":"Excite - Rotation","np":8,"mn":"Pseudo/BNCA2506f0b33","ix":1,"en":1,"ef":[{"ty":7,"nm":"Enable","mn":"Pseudo/BNCA2506f0b33-0001","ix":1,"v":{"a":0,"k":1,"ix":1}},{"ty":6,"nm":"Properties","mn":"Pseudo/BNCA2506f0b33-0002","ix":2,"v":0},{"ty":0,"nm":"Overshoot","mn":"Pseudo/BNCA2506f0b33-0003","ix":3,"v":{"a":0,"k":5,"ix":3,"x":"var $bm_rt;\n$bm_rt = clamp(value, 0, 100);"}},{"ty":0,"nm":"Bounce","mn":"Pseudo/BNCA2506f0b33-0004","ix":4,"v":{"a":0,"k":30,"ix":4,"x":"var $bm_rt;\n$bm_rt = clamp(value, 0, 100);"}},{"ty":0,"nm":"Friction","mn":"Pseudo/BNCA2506f0b33-0005","ix":5,"v":{"a":0,"k":100,"ix":5,"x":"var $bm_rt;\n$bm_rt = clamp(value, 0, 100);"}},{"ty":6,"nm":"","mn":"Pseudo/BNCA2506f0b33-0006","ix":6,"v":0}]}],"shapes":[{"ty":"gr","it":[{"ind":0,"ty":"sh","ix":1,"ks":{"a":0,"k":{"i":[[-24.492,-28.634],[17.06,-14.043],[24.492,28.634],[-17.06,14.043]],"o":[[24.492,28.634],[-17.06,14.043],[-24.492,-28.634],[17.06,-14.044]],"v":[[30.889,-25.427],[44.346,51.847],[-30.889,25.428],[-44.346,-51.846]],"c":true},"ix":2},"nm":"Path 1","mn":"ADBE Vector Shape - Group","hd":false},{"ty":"st","c":{"a":0,"k":[0.019607843137,0.388235324037,0.392156892664,1],"ix":3},"o":{"a":0,"k":100,"ix":4},"w":{"a":0,"k":2,"ix":5},"lc":1,"lj":1,"ml":10,"bm":0,"nm":"Stroke 1","mn":"ADBE Vector Graphic - Stroke","hd":false},{"ty":"fl","c":{"a":0,"k":[0.776455269608,0.465318567613,0.254703028062,1],"ix":4},"o":{"a":0,"k":100,"ix":5},"r":1,"bm":0,"nm":"Fill 1","mn":"ADBE Vector Graphic - Fill","hd":false},{"ty":"tr","p":{"a":0,"k":[80.656,85.14],"ix":2},"a":{"a":0,"k":[0,0],"ix":1},"s":{"a":0,"k":[100,100],"ix":3},"r":{"a":0,"k":0,"ix":6},"o":{"a":0,"k":100,"ix":7},"sk":{"a":0,"k":0,"ix":4},"sa":{"a":0,"k":0,"ix":5},"nm":"Transform"}],"nm":"Group 1","np":3,"cix":2,"bm":0,"ix":1,"mn":"ADBE Vector Group","hd":false}],"ip":-4,"op":60,"st":-206.8,"bm":0},{"ddd":0,"ind":4,"ty":4,"nm":"Layer 1 Outlines 2","parent":1,"tt":2,"sr":1,"ks":{"o":{"a":0,"k":100,"ix":11},"r":{"a":0,"k":0,"ix":10,"x":"var $bm_rt;\nvar enable, amp, freq, decay, n, t, v;\ntry {\n    $bm_rt = enable = effect('Excite - Rotation')('Pseudo/BNCA2506f0b33-0001');\n    if (enable == 0) {\n        $bm_rt = value;\n    } else {\n        amp = $bm_div(effect('Excite - Rotation')('Pseudo/BNCA2506f0b33-0003'), 2.5);\n        freq = $bm_div(effect('Excite - Rotation')('Pseudo/BNCA2506f0b33-0004'), 20);\n        decay = $bm_div(effect('Excite - Rotation')('Pseudo/BNCA2506f0b33-0005'), 20);\n        n = 0, 0 < numKeys && (n = nearestKey(time).index, key(n).time > time && n--), t = 0 === n ? 0 : $bm_sub(time, key(n).time), $bm_rt = 0 < n ? (v = velocityAtTime($bm_sub(key(n).time, $bm_div(thisComp.frameDuration, 10))), $bm_sum(value, $bm_div($bm_mul($bm_mul($bm_div(v, 100), amp), Math.sin($bm_mul($bm_mul($bm_mul(freq, t), 2), Math.PI))), Math.exp($bm_mul(decay, t))))) : value;\n    }\n} catch (err) {\n    $bm_rt = value = value;\n}"},"p":{"a":0,"k":[54.602,106.975,0],"ix":2},"a":{"a":0,"k":[60,155.25,0],"ix":1},"s":{"a":1,"k":[{"i":{"x":[0.667,0.667,0.667],"y":[1,1,1]},"o":{"x":[0.333,0.333,0.333],"y":[0,0,0]},"t":51.001,"s":[180,180,100]},{"i":{"x":[0.833,0.833,0.833],"y":[0.833,0.833,1]},"o":{"x":[0.333,0.333,0.333],"y":[0,0,0]},"t":60.001,"s":[0,0,100]},{"i":{"x":[0.833,0.833,0.833],"y":[0.833,0.833,0.833]},"o":{"x":[0.167,0.167,0.167],"y":[0.167,0.167,0.167]},"t":342.8,"s":[180,180,100]},{"i":{"x":[0.833,0.833,0.833],"y":[0.833,0.833,0.833]},"o":{"x":[0.167,0.167,0.167],"y":[0.167,0.167,0.167]},"t":347.6,"s":[185,185,100]},{"i":{"x":[0.833,0.833,0.833],"y":[0.833,0.833,0.833]},"o":{"x":[0.167,0.167,0.167],"y":[0.167,0.167,0.167]},"t":354.8,"s":[180,180,100]},{"t":364.39921875,"s":[0,0,100]}],"ix":6,"x":"var $bm_rt;\nvar enable, amp, freq, decay, n, t, v;\ntry {\n    $bm_rt = enable = effect('Excite - Scale')('Pseudo/BNCA2506f0b33-0001');\n    if (enable == 0) {\n        $bm_rt = value;\n    } else {\n        amp = $bm_div(effect('Excite - Scale')('Pseudo/BNCA2506f0b33-0003'), 2.5);\n        freq = $bm_div(effect('Excite - Scale')('Pseudo/BNCA2506f0b33-0004'), 20);\n        decay = $bm_div(effect('Excite - Scale')('Pseudo/BNCA2506f0b33-0005'), 20);\n        n = 0, 0 < numKeys && (n = nearestKey(time).index, key(n).time > time && n--), t = 0 === n ? 0 : $bm_sub(time, key(n).time), $bm_rt = 0 < n ? (v = velocityAtTime($bm_sub(key(n).time, $bm_div(thisComp.frameDuration, 10))), $bm_sum(value, $bm_div($bm_mul($bm_mul($bm_div(v, 100), amp), Math.sin($bm_mul($bm_mul($bm_mul(freq, t), 2), Math.PI))), Math.exp($bm_mul(decay, t))))) : value;\n    }\n} catch (err) {\n    $bm_rt = value = value;\n}"}},"ao":0,"ef":[{"ty":5,"nm":"Excite - Rotation","np":8,"mn":"Pseudo/BNCA2506f0b33","ix":1,"en":1,"ef":[{"ty":7,"nm":"Enable","mn":"Pseudo/BNCA2506f0b33-0001","ix":1,"v":{"a":0,"k":1,"ix":1}},{"ty":6,"nm":"Properties","mn":"Pseudo/BNCA2506f0b33-0002","ix":2,"v":0},{"ty":0,"nm":"Overshoot","mn":"Pseudo/BNCA2506f0b33-0003","ix":3,"v":{"a":0,"k":5,"ix":3,"x":"var $bm_rt;\n$bm_rt = clamp(value, 0, 100);"}},{"ty":0,"nm":"Bounce","mn":"Pseudo/BNCA2506f0b33-0004","ix":4,"v":{"a":0,"k":30,"ix":4,"x":"var $bm_rt;\n$bm_rt = clamp(value, 0, 100);"}},{"ty":0,"nm":"Friction","mn":"Pseudo/BNCA2506f0b33-0005","ix":5,"v":{"a":0,"k":100,"ix":5,"x":"var $bm_rt;\n$bm_rt = clamp(value, 0, 100);"}},{"ty":6,"nm":"","mn":"Pseudo/BNCA2506f0b33-0006","ix":6,"v":0}]},{"ty":5,"nm":"Excite - Scale","np":8,"mn":"Pseudo/BNCA2506f0b33","ix":2,"en":1,"ef":[{"ty":7,"nm":"Enable","mn":"Pseudo/BNCA2506f0b33-0001","ix":1,"v":{"a":0,"k":1,"ix":1}},{"ty":6,"nm":"Properties","mn":"Pseudo/BNCA2506f0b33-0002","ix":2,"v":0},{"ty":0,"nm":"Overshoot","mn":"Pseudo/BNCA2506f0b33-0003","ix":3,"v":{"a":0,"k":5,"ix":3,"x":"var $bm_rt;\n$bm_rt = clamp(value, 0, 100);"}},{"ty":0,"nm":"Bounce","mn":"Pseudo/BNCA2506f0b33-0004","ix":4,"v":{"a":0,"k":30,"ix":4,"x":"var $bm_rt;\n$bm_rt = clamp(value, 0, 100);"}},{"ty":0,"nm":"Friction","mn":"Pseudo/BNCA2506f0b33-0005","ix":5,"v":{"a":0,"k":100,"ix":5,"x":"var $bm_rt;\n$bm_rt = clamp(value, 0, 100);"}},{"ty":6,"nm":"","mn":"Pseudo/BNCA2506f0b33-0006","ix":6,"v":0}]}],"shapes":[{"ty":"gr","it":[{"ind":0,"ty":"sh","ix":1,"ks":{"a":0,"k":{"i":[[0,-37.379],[22.27,0],[0,37.379],[-22.27,0]],"o":[[0,37.379],[-22.271,0],[0,-37.379],[22.27,0]],"v":[[40.324,0],[0.001,67.681],[-40.324,0],[0.001,-67.681]],"c":true},"ix":2},"nm":"Path 1","mn":"ADBE Vector Shape - Group","hd":false},{"ty":"st","c":{"a":0,"k":[1,1,1,1],"ix":3},"o":{"a":0,"k":100,"ix":4},"w":{"a":0,"k":7.7,"ix":5},"lc":1,"lj":1,"ml":10,"bm":0,"nm":"Stroke 1","mn":"ADBE Vector Graphic - Stroke","hd":false},{"ty":"tr","p":{"a":0,"k":[59.573,86.931],"ix":2},"a":{"a":0,"k":[0,0],"ix":1},"s":{"a":0,"k":[100,100],"ix":3},"r":{"a":0,"k":0,"ix":6},"o":{"a":0,"k":100,"ix":7},"sk":{"a":0,"k":0,"ix":4},"sa":{"a":0,"k":0,"ix":5},"nm":"Transform"}],"nm":"Group 1","np":3,"cix":2,"bm":0,"ix":1,"mn":"ADBE Vector Group","hd":false}],"ip":-4,"op":60,"st":-206.8,"bm":0},{"ddd":0,"ind":5,"ty":0,"nm":"LEAVES MASK - REVERSE","td":1,"refId":"comp_1","sr":1,"ks":{"o":{"a":0,"k":100,"ix":11},"r":{"a":0,"k":0,"ix":10},"p":{"a":0,"k":[52.399,40.256,0],"ix":2},"a":{"a":0,"k":[400,293,0],"ix":1},"s":{"a":0,"k":[25,25,100],"ix":6}},"ao":0,"w":800,"h":586,"ip":0,"op":480,"st":0,"bm":0},{"ddd":0,"ind":6,"ty":4,"nm":"logo_RAW FILE Outlines 2","parent":4,"tt":2,"sr":1,"ks":{"o":{"a":0,"k":100,"ix":11},"r":{"a":1,"k":[{"i":{"x":[0.667],"y":[1]},"o":{"x":[0.333],"y":[0]},"t":42.801,"s":[0]},{"t":53,"s":[-38]}],"ix":10},"p":{"a":1,"k":[{"i":{"x":0.667,"y":1},"o":{"x":0.333,"y":0},"t":42.801,"s":[41.737,148.646,0],"to":[2.424,1.212,0],"ti":[-2.424,-1.212,0]},{"t":53,"s":[56.282,155.919,0]}],"ix":2},"a":{"a":0,"k":[240.897,278.09,0],"ix":1},"s":{"a":0,"k":[98.728,98.728,100],"ix":6}},"ao":0,"shapes":[{"ty":"gr","it":[{"ind":0,"ty":"sh","ix":1,"ks":{"a":0,"k":{"i":[[24.492,-28.634],[17.06,14.044],[-24.492,28.634],[-17.06,-14.043]],"o":[[-24.492,28.634],[-17.06,-14.043],[24.492,-28.634],[17.06,14.043]],"v":[[30.889,25.427],[-44.346,51.846],[-30.889,-25.428],[44.346,-51.847]],"c":true},"ix":2},"nm":"Path 1","mn":"ADBE Vector Shape - Group","hd":false},{"ty":"st","c":{"a":0,"k":[1,1,1,1],"ix":3},"o":{"a":0,"k":100,"ix":4},"w":{"a":0,"k":7.7,"ix":5},"lc":1,"lj":1,"ml":10,"bm":0,"nm":"Stroke 1","mn":"ADBE Vector Graphic - Stroke","hd":false},{"ty":"tr","p":{"a":0,"k":[285.367,227.131],"ix":2},"a":{"a":0,"k":[0,0],"ix":1},"s":{"a":0,"k":[100,100],"ix":3},"r":{"a":0,"k":0,"ix":6},"o":{"a":0,"k":100,"ix":7},"sk":{"a":0,"k":0,"ix":4},"sa":{"a":0,"k":0,"ix":5},"nm":"Transform"}],"nm":"Group 3","np":3,"cix":2,"bm":0,"ix":1,"mn":"ADBE Vector Group","hd":false}],"ip":-4,"op":60,"st":14,"bm":0},{"ddd":0,"ind":8,"ty":3,"nm":"NULL","sr":1,"ks":{"o":{"a":0,"k":0,"ix":11},"r":{"a":0,"k":0,"ix":10},"p":{"a":0,"k":[47.5,54.5,0],"ix":2},"a":{"a":0,"k":[50,50,0],"ix":1},"s":{"a":0,"k":[25,25,100],"ix":6}},"ao":0,"ip":48,"op":230,"st":48,"bm":0},{"ddd":0,"ind":9,"ty":4,"nm":"Layer 2 Outlines","parent":11,"sr":1,"ks":{"o":{"a":0,"k":100,"ix":11},"r":{"a":1,"k":[{"i":{"x":[0.833],"y":[0.833]},"o":{"x":[0.167],"y":[0.167]},"t":67.2,"s":[40]},{"i":{"x":[0.833],"y":[0.833]},"o":{"x":[0.167],"y":[0.167]},"t":76.8,"s":[0]},{"i":{"x":[0.833],"y":[0.833]},"o":{"x":[0.167],"y":[0.167]},"t":372.001,"s":[0]},{"i":{"x":[0.833],"y":[0.833]},"o":{"x":[0.167],"y":[0.167]},"t":376.8,"s":[-1]},{"i":{"x":[0.833],"y":[0.833]},"o":{"x":[0.167],"y":[0.167]},"t":381.6,"s":[-1]},{"t":391.2,"s":[40]}],"ix":10,"x":"var $bm_rt;\nvar enable, amp, freq, decay, n, t, v;\ntry {\n    $bm_rt = enable = effect('Excite - Rotation')('Pseudo/BNCA2506f0b33-0001');\n    if (enable == 0) {\n        $bm_rt = value;\n    } else {\n        amp = $bm_div(effect('Excite - Rotation')('Pseudo/BNCA2506f0b33-0003'), 2.5);\n        freq = $bm_div(effect('Excite - Rotation')('Pseudo/BNCA2506f0b33-0004'), 20);\n        decay = $bm_div(effect('Excite - Rotation')('Pseudo/BNCA2506f0b33-0005'), 20);\n        n = 0, 0 < numKeys && (n = nearestKey(time).index, key(n).time > time && n--), t = 0 === n ? 0 : $bm_sub(time, key(n).time), $bm_rt = 0 < n ? (v = velocityAtTime($bm_sub(key(n).time, $bm_div(thisComp.frameDuration, 10))), $bm_sum(value, $bm_div($bm_mul($bm_mul($bm_div(v, 100), amp), Math.sin($bm_mul($bm_mul($bm_mul(freq, t), 2), Math.PI))), Math.exp($bm_mul(decay, t))))) : value;\n    }\n} catch (err) {\n    $bm_rt = value = value;\n}"},"p":{"a":1,"k":[{"i":{"x":0.833,"y":0.833},"o":{"x":0.167,"y":0.167},"t":67.2,"s":[58.215,156.578,0],"to":[2.495,-1.023,0],"ti":[-2.495,1.023,0]},{"i":{"x":0.833,"y":0.833},"o":{"x":0.167,"y":0.167},"t":76.8,"s":[73.188,150.441,0],"to":[0,0,0],"ti":[0,0,0]},{"i":{"x":0.833,"y":0.833},"o":{"x":0.167,"y":0.167},"t":381.6,"s":[73.188,150.441,0],"to":[-2.495,1.023,0],"ti":[2.495,-1.023,0]},{"t":391.2,"s":[58.215,156.578,0]}],"ix":2},"a":{"a":1,"k":[{"i":{"x":0.833,"y":0.833},"o":{"x":0.167,"y":0.167},"t":76.8,"s":[124.156,138.64,0],"to":[0,0,0],"ti":[0,0,0]},{"t":381.600390625,"s":[124.156,138.64,0]}],"ix":1},"s":{"a":1,"k":[{"i":{"x":[0.833,0.833,0.833],"y":[0.833,0.833,0.833]},"o":{"x":[0.167,0.167,0.167],"y":[0.167,0.167,0.167]},"t":76.8,"s":[98.18,98.18,100]},{"t":381.600390625,"s":[98.18,98.18,100]}],"ix":6}},"ao":0,"ef":[{"ty":5,"nm":"Excite - Rotation","np":8,"mn":"Pseudo/BNCA2506f0b33","ix":1,"en":1,"ef":[{"ty":7,"nm":"Enable","mn":"Pseudo/BNCA2506f0b33-0001","ix":1,"v":{"a":0,"k":1,"ix":1}},{"ty":6,"nm":"Properties","mn":"Pseudo/BNCA2506f0b33-0002","ix":2,"v":0},{"ty":0,"nm":"Overshoot","mn":"Pseudo/BNCA2506f0b33-0003","ix":3,"v":{"a":0,"k":5,"ix":3,"x":"var $bm_rt;\n$bm_rt = clamp(value, 0, 100);"}},{"ty":0,"nm":"Bounce","mn":"Pseudo/BNCA2506f0b33-0004","ix":4,"v":{"a":0,"k":30,"ix":4,"x":"var $bm_rt;\n$bm_rt = clamp(value, 0, 100);"}},{"ty":0,"nm":"Friction","mn":"Pseudo/BNCA2506f0b33-0005","ix":5,"v":{"a":0,"k":100,"ix":5,"x":"var $bm_rt;\n$bm_rt = clamp(value, 0, 100);"}},{"ty":6,"nm":"","mn":"Pseudo/BNCA2506f0b33-0006","ix":6,"v":0}]}],"shapes":[{"ty":"gr","it":[{"ind":0,"ty":"sh","ix":1,"ks":{"a":0,"k":{"i":[[-24.492,-28.634],[17.06,-14.043],[24.492,28.634],[-17.06,14.043]],"o":[[24.492,28.634],[-17.06,14.043],[-24.492,-28.634],[17.06,-14.044]],"v":[[30.889,-25.427],[44.346,51.847],[-30.889,25.428],[-44.346,-51.846]],"c":true},"ix":2},"nm":"Path 1","mn":"ADBE Vector Shape - Group","hd":false},{"ty":"st","c":{"a":0,"k":[1,1,1,1],"ix":3},"o":{"a":0,"k":100,"ix":4},"w":{"a":0,"k":7.7,"ix":5},"lc":1,"lj":1,"ml":10,"bm":0,"nm":"Stroke 1","mn":"ADBE Vector Graphic - Stroke","hd":false},{"ty":"tr","p":{"a":0,"k":[80.656,85.14],"ix":2},"a":{"a":0,"k":[0,0],"ix":1},"s":{"a":0,"k":[100,100],"ix":3},"r":{"a":0,"k":0,"ix":6},"o":{"a":0,"k":100,"ix":7},"sk":{"a":0,"k":0,"ix":4},"sa":{"a":0,"k":0,"ix":5},"nm":"Transform"}],"nm":"Group 1","np":3,"cix":2,"bm":0,"ix":1,"mn":"ADBE Vector Group","hd":false}],"ip":48,"op":230,"st":-172.8,"bm":0},{"ddd":0,"ind":10,"ty":4,"nm":"Layer 2 Outlines 2","parent":11,"td":1,"sr":1,"ks":{"o":{"a":0,"k":100,"ix":11},"r":{"a":1,"k":[{"i":{"x":[0.833],"y":[0.833]},"o":{"x":[0.167],"y":[0.167]},"t":67.2,"s":[40]},{"i":{"x":[0.833],"y":[0.833]},"o":{"x":[0.167],"y":[0.167]},"t":76.8,"s":[0]},{"i":{"x":[0.833],"y":[0.833]},"o":{"x":[0.167],"y":[0.167]},"t":372.001,"s":[0]},{"i":{"x":[0.833],"y":[0.833]},"o":{"x":[0.167],"y":[0.167]},"t":376.8,"s":[-1]},{"i":{"x":[0.833],"y":[0.833]},"o":{"x":[0.167],"y":[0.167]},"t":381.6,"s":[-1]},{"t":391.2,"s":[40]}],"ix":10,"x":"var $bm_rt;\nvar enable, amp, freq, decay, n, t, v;\ntry {\n    $bm_rt = enable = effect('Excite - Rotation')('Pseudo/BNCA2506f0b33-0001');\n    if (enable == 0) {\n        $bm_rt = value;\n    } else {\n        amp = $bm_div(effect('Excite - Rotation')('Pseudo/BNCA2506f0b33-0003'), 2.5);\n        freq = $bm_div(effect('Excite - Rotation')('Pseudo/BNCA2506f0b33-0004'), 20);\n        decay = $bm_div(effect('Excite - Rotation')('Pseudo/BNCA2506f0b33-0005'), 20);\n        n = 0, 0 < numKeys && (n = nearestKey(time).index, key(n).time > time && n--), t = 0 === n ? 0 : $bm_sub(time, key(n).time), $bm_rt = 0 < n ? (v = velocityAtTime($bm_sub(key(n).time, $bm_div(thisComp.frameDuration, 10))), $bm_sum(value, $bm_div($bm_mul($bm_mul($bm_div(v, 100), amp), Math.sin($bm_mul($bm_mul($bm_mul(freq, t), 2), Math.PI))), Math.exp($bm_mul(decay, t))))) : value;\n    }\n} catch (err) {\n    $bm_rt = value = value;\n}"},"p":{"a":1,"k":[{"i":{"x":0.833,"y":0.833},"o":{"x":0.167,"y":0.167},"t":67.2,"s":[58.215,156.578,0],"to":[2.495,-1.023,0],"ti":[-2.495,1.023,0]},{"i":{"x":0.833,"y":0.833},"o":{"x":0.167,"y":0.167},"t":76.8,"s":[73.188,150.441,0],"to":[0,0,0],"ti":[0,0,0]},{"i":{"x":0.833,"y":0.833},"o":{"x":0.167,"y":0.167},"t":381.6,"s":[73.188,150.441,0],"to":[-2.495,1.023,0],"ti":[2.495,-1.023,0]},{"t":391.2,"s":[58.215,156.578,0]}],"ix":2},"a":{"a":1,"k":[{"i":{"x":0.833,"y":0.833},"o":{"x":0.167,"y":0.167},"t":76.8,"s":[124.156,138.64,0],"to":[0,0,0],"ti":[0,0,0]},{"t":381.600390625,"s":[124.156,138.64,0]}],"ix":1},"s":{"a":1,"k":[{"i":{"x":[0.833,0.833,0.833],"y":[0.833,0.833,0.833]},"o":{"x":[0.167,0.167,0.167],"y":[0.167,0.167,0.167]},"t":76.8,"s":[98.18,98.18,100]},{"t":381.600390625,"s":[98.18,98.18,100]}],"ix":6}},"ao":0,"ef":[{"ty":5,"nm":"Excite - Rotation","np":8,"mn":"Pseudo/BNCA2506f0b33","ix":1,"en":1,"ef":[{"ty":7,"nm":"Enable","mn":"Pseudo/BNCA2506f0b33-0001","ix":1,"v":{"a":0,"k":1,"ix":1}},{"ty":6,"nm":"Properties","mn":"Pseudo/BNCA2506f0b33-0002","ix":2,"v":0},{"ty":0,"nm":"Overshoot","mn":"Pseudo/BNCA2506f0b33-0003","ix":3,"v":{"a":0,"k":5,"ix":3,"x":"var $bm_rt;\n$bm_rt = clamp(value, 0, 100);"}},{"ty":0,"nm":"Bounce","mn":"Pseudo/BNCA2506f0b33-0004","ix":4,"v":{"a":0,"k":30,"ix":4,"x":"var $bm_rt;\n$bm_rt = clamp(value, 0, 100);"}},{"ty":0,"nm":"Friction","mn":"Pseudo/BNCA2506f0b33-0005","ix":5,"v":{"a":0,"k":100,"ix":5,"x":"var $bm_rt;\n$bm_rt = clamp(value, 0, 100);"}},{"ty":6,"nm":"","mn":"Pseudo/BNCA2506f0b33-0006","ix":6,"v":0}]}],"shapes":[{"ty":"gr","it":[{"ind":0,"ty":"sh","ix":1,"ks":{"a":0,"k":{"i":[[-24.492,-28.634],[17.06,-14.043],[24.492,28.634],[-17.06,14.043]],"o":[[24.492,28.634],[-17.06,14.043],[-24.492,-28.634],[17.06,-14.044]],"v":[[30.889,-25.427],[44.346,51.847],[-30.889,25.428],[-44.346,-51.846]],"c":true},"ix":2},"nm":"Path 1","mn":"ADBE Vector Shape - Group","hd":false},{"ty":"st","c":{"a":0,"k":[0.019607843137,0.388235324037,0.392156892664,1],"ix":3},"o":{"a":0,"k":100,"ix":4},"w":{"a":0,"k":2,"ix":5},"lc":1,"lj":1,"ml":10,"bm":0,"nm":"Stroke 1","mn":"ADBE Vector Graphic - Stroke","hd":false},{"ty":"fl","c":{"a":0,"k":[0.776455269608,0.465318567613,0.254703028062,1],"ix":4},"o":{"a":0,"k":100,"ix":5},"r":1,"bm":0,"nm":"Fill 1","mn":"ADBE Vector Graphic - Fill","hd":false},{"ty":"tr","p":{"a":0,"k":[80.656,85.14],"ix":2},"a":{"a":0,"k":[0,0],"ix":1},"s":{"a":0,"k":[100,100],"ix":3},"r":{"a":0,"k":0,"ix":6},"o":{"a":0,"k":100,"ix":7},"sk":{"a":0,"k":0,"ix":4},"sa":{"a":0,"k":0,"ix":5},"nm":"Transform"}],"nm":"Group 1","np":3,"cix":2,"bm":0,"ix":1,"mn":"ADBE Vector Group","hd":false}],"ip":48,"op":230,"st":-172.8,"bm":0},{"ddd":0,"ind":11,"ty":4,"nm":"Layer 1 Outlines","parent":8,"tt":2,"sr":1,"ks":{"o":{"a":0,"k":100,"ix":11},"r":{"a":0,"k":0,"ix":10,"x":"var $bm_rt;\nvar enable, amp, freq, decay, n, t, v;\ntry {\n    $bm_rt = enable = effect('Excite - Rotation')('Pseudo/BNCA2506f0b33-0001');\n    if (enable == 0) {\n        $bm_rt = value;\n    } else {\n        amp = $bm_div(effect('Excite - Rotation')('Pseudo/BNCA2506f0b33-0003'), 2.5);\n        freq = $bm_div(effect('Excite - Rotation')('Pseudo/BNCA2506f0b33-0004'), 20);\n        decay = $bm_div(effect('Excite - Rotation')('Pseudo/BNCA2506f0b33-0005'), 20);\n        n = 0, 0 < numKeys && (n = nearestKey(time).index, key(n).time > time && n--), t = 0 === n ? 0 : $bm_sub(time, key(n).time), $bm_rt = 0 < n ? (v = velocityAtTime($bm_sub(key(n).time, $bm_div(thisComp.frameDuration, 10))), $bm_sum(value, $bm_div($bm_mul($bm_mul($bm_div(v, 100), amp), Math.sin($bm_mul($bm_mul($bm_mul(freq, t), 2), Math.PI))), Math.exp($bm_mul(decay, t))))) : value;\n    }\n} catch (err) {\n    $bm_rt = value = value;\n}"},"p":{"a":0,"k":[54.602,106.975,0],"ix":2},"a":{"a":0,"k":[60,155.25,0],"ix":1},"s":{"a":1,"k":[{"i":{"x":[0.833,0.833,0.833],"y":[0.833,0.833,0.833]},"o":{"x":[0.167,0.167,0.167],"y":[0.167,0.167,0.167]},"t":60.001,"s":[0,0,100]},{"i":{"x":[0.833,0.833,0.833],"y":[0.833,0.833,0.833]},"o":{"x":[0.167,0.167,0.167],"y":[0.167,0.167,0.167]},"t":69.6,"s":[180,180,100]},{"i":{"x":[0.833,0.833,0.833],"y":[0.833,0.833,0.833]},"o":{"x":[0.167,0.167,0.167],"y":[0.167,0.167,0.167]},"t":376.8,"s":[180,180,100]},{"i":{"x":[0.833,0.833,0.833],"y":[0.833,0.833,0.833]},"o":{"x":[0.167,0.167,0.167],"y":[0.167,0.167,0.167]},"t":381.6,"s":[185,185,100]},{"i":{"x":[0.833,0.833,0.833],"y":[0.833,0.833,0.833]},"o":{"x":[0.167,0.167,0.167],"y":[0.167,0.167,0.167]},"t":388.8,"s":[180,180,100]},{"t":398.39921875,"s":[0,0,100]}],"ix":6,"x":"var $bm_rt;\nvar enable, amp, freq, decay, n, t, v;\ntry {\n    $bm_rt = enable = effect('Excite - Scale')('Pseudo/BNCA2506f0b33-0001');\n    if (enable == 0) {\n        $bm_rt = value;\n    } else {\n        amp = $bm_div(effect('Excite - Scale')('Pseudo/BNCA2506f0b33-0003'), 2.5);\n        freq = $bm_div(effect('Excite - Scale')('Pseudo/BNCA2506f0b33-0004'), 20);\n        decay = $bm_div(effect('Excite - Scale')('Pseudo/BNCA2506f0b33-0005'), 20);\n        n = 0, 0 < numKeys && (n = nearestKey(time).index, key(n).time > time && n--), t = 0 === n ? 0 : $bm_sub(time, key(n).time), $bm_rt = 0 < n ? (v = velocityAtTime($bm_sub(key(n).time, $bm_div(thisComp.frameDuration, 10))), $bm_sum(value, $bm_div($bm_mul($bm_mul($bm_div(v, 100), amp), Math.sin($bm_mul($bm_mul($bm_mul(freq, t), 2), Math.PI))), Math.exp($bm_mul(decay, t))))) : value;\n    }\n} catch (err) {\n    $bm_rt = value = value;\n}"}},"ao":0,"ef":[{"ty":5,"nm":"Excite - Rotation","np":8,"mn":"Pseudo/BNCA2506f0b33","ix":1,"en":1,"ef":[{"ty":7,"nm":"Enable","mn":"Pseudo/BNCA2506f0b33-0001","ix":1,"v":{"a":0,"k":1,"ix":1}},{"ty":6,"nm":"Properties","mn":"Pseudo/BNCA2506f0b33-0002","ix":2,"v":0},{"ty":0,"nm":"Overshoot","mn":"Pseudo/BNCA2506f0b33-0003","ix":3,"v":{"a":0,"k":5,"ix":3,"x":"var $bm_rt;\n$bm_rt = clamp(value, 0, 100);"}},{"ty":0,"nm":"Bounce","mn":"Pseudo/BNCA2506f0b33-0004","ix":4,"v":{"a":0,"k":30,"ix":4,"x":"var $bm_rt;\n$bm_rt = clamp(value, 0, 100);"}},{"ty":0,"nm":"Friction","mn":"Pseudo/BNCA2506f0b33-0005","ix":5,"v":{"a":0,"k":100,"ix":5,"x":"var $bm_rt;\n$bm_rt = clamp(value, 0, 100);"}},{"ty":6,"nm":"","mn":"Pseudo/BNCA2506f0b33-0006","ix":6,"v":0}]},{"ty":5,"nm":"Excite - Scale","np":8,"mn":"Pseudo/BNCA2506f0b33","ix":2,"en":1,"ef":[{"ty":7,"nm":"Enable","mn":"Pseudo/BNCA2506f0b33-0001","ix":1,"v":{"a":0,"k":1,"ix":1}},{"ty":6,"nm":"Properties","mn":"Pseudo/BNCA2506f0b33-0002","ix":2,"v":0},{"ty":0,"nm":"Overshoot","mn":"Pseudo/BNCA2506f0b33-0003","ix":3,"v":{"a":0,"k":5,"ix":3,"x":"var $bm_rt;\n$bm_rt = clamp(value, 0, 100);"}},{"ty":0,"nm":"Bounce","mn":"Pseudo/BNCA2506f0b33-0004","ix":4,"v":{"a":0,"k":30,"ix":4,"x":"var $bm_rt;\n$bm_rt = clamp(value, 0, 100);"}},{"ty":0,"nm":"Friction","mn":"Pseudo/BNCA2506f0b33-0005","ix":5,"v":{"a":0,"k":100,"ix":5,"x":"var $bm_rt;\n$bm_rt = clamp(value, 0, 100);"}},{"ty":6,"nm":"","mn":"Pseudo/BNCA2506f0b33-0006","ix":6,"v":0}]}],"shapes":[{"ty":"gr","it":[{"ind":0,"ty":"sh","ix":1,"ks":{"a":0,"k":{"i":[[0,-37.379],[22.27,0],[0,37.379],[-22.27,0]],"o":[[0,37.379],[-22.271,0],[0,-37.379],[22.27,0]],"v":[[40.324,0],[0.001,67.681],[-40.324,0],[0.001,-67.681]],"c":true},"ix":2},"nm":"Path 1","mn":"ADBE Vector Shape - Group","hd":false},{"ty":"st","c":{"a":0,"k":[1,1,1,1],"ix":3},"o":{"a":0,"k":100,"ix":4},"w":{"a":0,"k":7.7,"ix":5},"lc":1,"lj":1,"ml":10,"bm":0,"nm":"Stroke 1","mn":"ADBE Vector Graphic - Stroke","hd":false},{"ty":"tr","p":{"a":0,"k":[59.573,86.931],"ix":2},"a":{"a":0,"k":[0,0],"ix":1},"s":{"a":0,"k":[100,100],"ix":3},"r":{"a":0,"k":0,"ix":6},"o":{"a":0,"k":100,"ix":7},"sk":{"a":0,"k":0,"ix":4},"sa":{"a":0,"k":0,"ix":5},"nm":"Transform"}],"nm":"Group 1","np":3,"cix":2,"bm":0,"ix":1,"mn":"ADBE Vector Group","hd":false}],"ip":48,"op":230,"st":-172.8,"bm":0},{"ddd":0,"ind":12,"ty":0,"nm":"LEAVES MASK","td":1,"refId":"comp_2","sr":1,"ks":{"o":{"a":0,"k":100,"ix":11},"r":{"a":0,"k":0,"ix":10},"p":{"a":0,"k":[52.399,40.256,0],"ix":2},"a":{"a":0,"k":[400,293,0],"ix":1},"s":{"a":0,"k":[25,25,100],"ix":6}},"ao":0,"w":800,"h":586,"ip":48,"op":230,"st":48,"bm":0},{"ddd":0,"ind":13,"ty":4,"nm":"logo_RAW FILE Outlines","parent":11,"tt":2,"sr":1,"ks":{"o":{"a":0,"k":100,"ix":11},"r":{"a":1,"k":[{"i":{"x":[0.833],"y":[0.833]},"o":{"x":[0.167],"y":[0.167]},"t":67.199,"s":[-38]},{"t":76.80078125,"s":[0]}],"ix":10},"p":{"a":1,"k":[{"i":{"x":0.833,"y":0.833},"o":{"x":0.167,"y":0.167},"t":67.199,"s":[56.282,155.919,0],"to":[-2.424,-1.212,0],"ti":[2.424,1.212,0]},{"t":76.80078125,"s":[41.737,148.646,0]}],"ix":2},"a":{"a":0,"k":[240.897,278.09,0],"ix":1},"s":{"a":0,"k":[98.728,98.728,100],"ix":6}},"ao":0,"shapes":[{"ty":"gr","it":[{"ind":0,"ty":"sh","ix":1,"ks":{"a":0,"k":{"i":[[24.492,-28.634],[17.06,14.044],[-24.492,28.634],[-17.06,-14.043]],"o":[[-24.492,28.634],[-17.06,-14.043],[24.492,-28.634],[17.06,14.043]],"v":[[30.889,25.427],[-44.346,51.846],[-30.889,-25.428],[44.346,-51.847]],"c":true},"ix":2},"nm":"Path 1","mn":"ADBE Vector Shape - Group","hd":false},{"ty":"st","c":{"a":0,"k":[1,1,1,1],"ix":3},"o":{"a":0,"k":100,"ix":4},"w":{"a":0,"k":7.7,"ix":5},"lc":1,"lj":1,"ml":10,"bm":0,"nm":"Stroke 1","mn":"ADBE Vector Graphic - Stroke","hd":false},{"ty":"tr","p":{"a":0,"k":[285.367,227.131],"ix":2},"a":{"a":0,"k":[0,0],"ix":1},"s":{"a":0,"k":[100,100],"ix":3},"r":{"a":0,"k":0,"ix":6},"o":{"a":0,"k":100,"ix":7},"sk":{"a":0,"k":0,"ix":4},"sa":{"a":0,"k":0,"ix":5},"nm":"Transform"}],"nm":"Group 3","np":3,"cix":2,"bm":0,"ix":1,"mn":"ADBE Vector Group","hd":false}],"ip":69.6,"op":230,"st":48,"bm":0}]},{"id":"comp_1","layers":[{"ddd":0,"ind":1,"ty":4,"nm":"Layer 2 Outlines 3","parent":2,"sr":1,"ks":{"o":{"a":0,"k":100,"ix":11},"r":{"a":1,"k":[{"i":{"x":[0.833],"y":[0.833]},"o":{"x":[0.167],"y":[0.167]},"t":43.2,"s":[0]},{"t":52.8,"s":[40]}],"ix":10,"x":"var $bm_rt;\nvar enable, amp, freq, decay, n, t, v;\ntry {\n    $bm_rt = enable = effect('Excite - Rotation')('Pseudo/BNCA2506f0b33-0001');\n    if (enable == 0) {\n        $bm_rt = value;\n    } else {\n        amp = $bm_div(effect('Excite - Rotation')('Pseudo/BNCA2506f0b33-0003'), 2.5);\n        freq = $bm_div(effect('Excite - Rotation')('Pseudo/BNCA2506f0b33-0004'), 20);\n        decay = $bm_div(effect('Excite - Rotation')('Pseudo/BNCA2506f0b33-0005'), 20);\n        n = 0, 0 < numKeys && (n = nearestKey(time).index, key(n).time > time && n--), t = 0 === n ? 0 : $bm_sub(time, key(n).time), $bm_rt = 0 < n ? (v = velocityAtTime($bm_sub(key(n).time, $bm_div(thisComp.frameDuration, 10))), $bm_sum(value, $bm_div($bm_mul($bm_mul($bm_div(v, 100), amp), Math.sin($bm_mul($bm_mul($bm_mul(freq, t), 2), Math.PI))), Math.exp($bm_mul(decay, t))))) : value;\n    }\n} catch (err) {\n    $bm_rt = value = value;\n}"},"p":{"a":1,"k":[{"i":{"x":0.833,"y":0.833},"o":{"x":0.167,"y":0.167},"t":43.2,"s":[73.432,150.352,0],"to":[-2.542,1.042,0],"ti":[2.542,-1.042,0]},{"t":52.8,"s":[58.182,156.602,0]}],"ix":2},"a":{"a":0,"k":[124.156,138.64,0],"ix":1},"s":{"a":0,"k":[100,100,100],"ix":6}},"ao":0,"ef":[{"ty":5,"nm":"Excite - Rotation","np":8,"mn":"Pseudo/BNCA2506f0b33","ix":1,"en":1,"ef":[{"ty":7,"nm":"Enable","mn":"Pseudo/BNCA2506f0b33-0001","ix":1,"v":{"a":0,"k":1,"ix":1}},{"ty":6,"nm":"Properties","mn":"Pseudo/BNCA2506f0b33-0002","ix":2,"v":0},{"ty":0,"nm":"Overshoot","mn":"Pseudo/BNCA2506f0b33-0003","ix":3,"v":{"a":0,"k":5,"ix":3,"x":"var $bm_rt;\n$bm_rt = clamp(value, 0, 100);"}},{"ty":0,"nm":"Bounce","mn":"Pseudo/BNCA2506f0b33-0004","ix":4,"v":{"a":0,"k":30,"ix":4,"x":"var $bm_rt;\n$bm_rt = clamp(value, 0, 100);"}},{"ty":0,"nm":"Friction","mn":"Pseudo/BNCA2506f0b33-0005","ix":5,"v":{"a":0,"k":100,"ix":5,"x":"var $bm_rt;\n$bm_rt = clamp(value, 0, 100);"}},{"ty":6,"nm":"","mn":"Pseudo/BNCA2506f0b33-0006","ix":6,"v":0}]}],"shapes":[{"ty":"gr","it":[{"ind":0,"ty":"sh","ix":1,"ks":{"a":0,"k":{"i":[[-24.492,-28.634],[17.06,-14.043],[24.492,28.634],[-17.06,14.043]],"o":[[24.492,28.634],[-17.06,14.043],[-24.492,-28.634],[17.06,-14.044]],"v":[[30.889,-25.427],[44.346,51.847],[-30.889,25.428],[-44.346,-51.846]],"c":true},"ix":2},"nm":"Path 1","mn":"ADBE Vector Shape - Group","hd":false},{"ty":"st","c":{"a":0,"k":[0.019607843137,0.388235324037,0.392156892664,1],"ix":3},"o":{"a":0,"k":100,"ix":4},"w":{"a":0,"k":2,"ix":5},"lc":1,"lj":1,"ml":10,"bm":0,"nm":"Stroke 1","mn":"ADBE Vector Graphic - Stroke","hd":false},{"ty":"fl","c":{"a":0,"k":[0.776455269608,0.465318567613,0.254703028062,1],"ix":4},"o":{"a":0,"k":100,"ix":5},"r":1,"bm":0,"nm":"Fill 1","mn":"ADBE Vector Graphic - Fill","hd":false},{"ty":"tr","p":{"a":0,"k":[80.656,85.14],"ix":2},"a":{"a":0,"k":[0,0],"ix":1},"s":{"a":0,"k":[100,100],"ix":3},"r":{"a":0,"k":0,"ix":6},"o":{"a":0,"k":100,"ix":7},"sk":{"a":0,"k":0,"ix":4},"sa":{"a":0,"k":0,"ix":5},"nm":"Transform"}],"nm":"Group 1","np":3,"cix":2,"bm":0,"ix":1,"mn":"ADBE Vector Group","hd":false}],"ip":0,"op":487.2,"st":-220.8,"bm":0},{"ddd":0,"ind":2,"ty":4,"nm":"Layer 1 Outlines 2","sr":1,"ks":{"o":{"a":0,"k":100,"ix":11},"r":{"a":0,"k":0,"ix":10,"x":"var $bm_rt;\nvar enable, amp, freq, decay, n, t, v;\ntry {\n    $bm_rt = enable = effect('Excite - Rotation')('Pseudo/BNCA2506f0b33-0001');\n    if (enable == 0) {\n        $bm_rt = value;\n    } else {\n        amp = $bm_div(effect('Excite - Rotation')('Pseudo/BNCA2506f0b33-0003'), 2.5);\n        freq = $bm_div(effect('Excite - Rotation')('Pseudo/BNCA2506f0b33-0004'), 20);\n        decay = $bm_div(effect('Excite - Rotation')('Pseudo/BNCA2506f0b33-0005'), 20);\n        n = 0, 0 < numKeys && (n = nearestKey(time).index, key(n).time > time && n--), t = 0 === n ? 0 : $bm_sub(time, key(n).time), $bm_rt = 0 < n ? (v = velocityAtTime($bm_sub(key(n).time, $bm_div(thisComp.frameDuration, 10))), $bm_sum(value, $bm_div($bm_mul($bm_mul($bm_div(v, 100), amp), Math.sin($bm_mul($bm_mul($bm_mul(freq, t), 2), Math.PI))), Math.exp($bm_mul(decay, t))))) : value;\n    }\n} catch (err) {\n    $bm_rt = value = value;\n}"},"p":{"a":0,"k":[385.005,406.95,0],"ix":2},"a":{"a":0,"k":[60,155.25,0],"ix":1},"s":{"a":1,"k":[{"i":{"x":[0.833,0.833,0.833],"y":[0.833,0.833,0.833]},"o":{"x":[0.167,0.167,0.167],"y":[0.167,0.167,0.167]},"t":50.4,"s":[180,180,100]},{"t":60,"s":[0,0,100]}],"ix":6,"x":"var $bm_rt;\nvar enable, amp, freq, decay, n, t, v;\ntry {\n    $bm_rt = enable = effect('Excite - Scale')('Pseudo/BNCA2506f0b33-0001');\n    if (enable == 0) {\n        $bm_rt = value;\n    } else {\n        amp = $bm_div(effect('Excite - Scale')('Pseudo/BNCA2506f0b33-0003'), 2.5);\n        freq = $bm_div(effect('Excite - Scale')('Pseudo/BNCA2506f0b33-0004'), 20);\n        decay = $bm_div(effect('Excite - Scale')('Pseudo/BNCA2506f0b33-0005'), 20);\n        n = 0, 0 < numKeys && (n = nearestKey(time).index, key(n).time > time && n--), t = 0 === n ? 0 : $bm_sub(time, key(n).time), $bm_rt = 0 < n ? (v = velocityAtTime($bm_sub(key(n).time, $bm_div(thisComp.frameDuration, 10))), $bm_sum(value, $bm_div($bm_mul($bm_mul($bm_div(v, 100), amp), Math.sin($bm_mul($bm_mul($bm_mul(freq, t), 2), Math.PI))), Math.exp($bm_mul(decay, t))))) : value;\n    }\n} catch (err) {\n    $bm_rt = value = value;\n}"}},"ao":0,"ef":[{"ty":5,"nm":"Excite - Rotation","np":8,"mn":"Pseudo/BNCA2506f0b33","ix":1,"en":1,"ef":[{"ty":7,"nm":"Enable","mn":"Pseudo/BNCA2506f0b33-0001","ix":1,"v":{"a":0,"k":1,"ix":1}},{"ty":6,"nm":"Properties","mn":"Pseudo/BNCA2506f0b33-0002","ix":2,"v":0},{"ty":0,"nm":"Overshoot","mn":"Pseudo/BNCA2506f0b33-0003","ix":3,"v":{"a":0,"k":5,"ix":3,"x":"var $bm_rt;\n$bm_rt = clamp(value, 0, 100);"}},{"ty":0,"nm":"Bounce","mn":"Pseudo/BNCA2506f0b33-0004","ix":4,"v":{"a":0,"k":30,"ix":4,"x":"var $bm_rt;\n$bm_rt = clamp(value, 0, 100);"}},{"ty":0,"nm":"Friction","mn":"Pseudo/BNCA2506f0b33-0005","ix":5,"v":{"a":0,"k":100,"ix":5,"x":"var $bm_rt;\n$bm_rt = clamp(value, 0, 100);"}},{"ty":6,"nm":"","mn":"Pseudo/BNCA2506f0b33-0006","ix":6,"v":0}]},{"ty":5,"nm":"Excite - Scale","np":8,"mn":"Pseudo/BNCA2506f0b33","ix":2,"en":1,"ef":[{"ty":7,"nm":"Enable","mn":"Pseudo/BNCA2506f0b33-0001","ix":1,"v":{"a":0,"k":1,"ix":1}},{"ty":6,"nm":"Properties","mn":"Pseudo/BNCA2506f0b33-0002","ix":2,"v":0},{"ty":0,"nm":"Overshoot","mn":"Pseudo/BNCA2506f0b33-0003","ix":3,"v":{"a":0,"k":5,"ix":3,"x":"var $bm_rt;\n$bm_rt = clamp(value, 0, 100);"}},{"ty":0,"nm":"Bounce","mn":"Pseudo/BNCA2506f0b33-0004","ix":4,"v":{"a":0,"k":30,"ix":4,"x":"var $bm_rt;\n$bm_rt = clamp(value, 0, 100);"}},{"ty":0,"nm":"Friction","mn":"Pseudo/BNCA2506f0b33-0005","ix":5,"v":{"a":0,"k":100,"ix":5,"x":"var $bm_rt;\n$bm_rt = clamp(value, 0, 100);"}},{"ty":6,"nm":"","mn":"Pseudo/BNCA2506f0b33-0006","ix":6,"v":0}]}],"shapes":[{"ty":"gr","it":[{"ind":0,"ty":"sh","ix":1,"ks":{"a":0,"k":{"i":[[0,-37.379],[22.27,0],[0,37.379],[-22.27,0]],"o":[[0,37.379],[-22.271,0],[0,-37.379],[22.27,0]],"v":[[40.324,0],[0.001,67.681],[-40.324,0],[0.001,-67.681]],"c":true},"ix":2},"nm":"Path 1","mn":"ADBE Vector Shape - Group","hd":false},{"ty":"st","c":{"a":0,"k":[0.019607843137,0.388235324037,0.392156892664,1],"ix":3},"o":{"a":0,"k":100,"ix":4},"w":{"a":0,"k":2,"ix":5},"lc":1,"lj":1,"ml":10,"bm":0,"nm":"Stroke 1","mn":"ADBE Vector Graphic - Stroke","hd":false},{"ty":"fl","c":{"a":0,"k":[0.776455269608,0.465318567613,0.254703028062,1],"ix":4},"o":{"a":0,"k":100,"ix":5},"r":1,"bm":0,"nm":"Fill 1","mn":"ADBE Vector Graphic - Fill","hd":false},{"ty":"tr","p":{"a":0,"k":[59.573,86.931],"ix":2},"a":{"a":0,"k":[0,0],"ix":1},"s":{"a":0,"k":[100,100],"ix":3},"r":{"a":0,"k":0,"ix":6},"o":{"a":0,"k":100,"ix":7},"sk":{"a":0,"k":0,"ix":4},"sa":{"a":0,"k":0,"ix":5},"nm":"Transform"}],"nm":"Group 1","np":3,"cix":2,"bm":0,"ix":1,"mn":"ADBE Vector Group","hd":false}],"ip":0,"op":487.2,"st":-220.8,"bm":0}]},{"id":"comp_2","layers":[{"ddd":0,"ind":1,"ty":4,"nm":"Layer 2 Outlines 3","parent":2,"sr":1,"ks":{"o":{"a":0,"k":100,"ix":11},"r":{"a":1,"k":[{"i":{"x":[0.833],"y":[0.833]},"o":{"x":[0.167],"y":[0.167]},"t":19.2,"s":[40]},{"t":28.8,"s":[0]}],"ix":10,"x":"var $bm_rt;\nvar enable, amp, freq, decay, n, t, v;\ntry {\n    $bm_rt = enable = effect('Excite - Rotation')('Pseudo/BNCA2506f0b33-0001');\n    if (enable == 0) {\n        $bm_rt = value;\n    } else {\n        amp = $bm_div(effect('Excite - Rotation')('Pseudo/BNCA2506f0b33-0003'), 2.5);\n        freq = $bm_div(effect('Excite - Rotation')('Pseudo/BNCA2506f0b33-0004'), 20);\n        decay = $bm_div(effect('Excite - Rotation')('Pseudo/BNCA2506f0b33-0005'), 20);\n        n = 0, 0 < numKeys && (n = nearestKey(time).index, key(n).time > time && n--), t = 0 === n ? 0 : $bm_sub(time, key(n).time), $bm_rt = 0 < n ? (v = velocityAtTime($bm_sub(key(n).time, $bm_div(thisComp.frameDuration, 10))), $bm_sum(value, $bm_div($bm_mul($bm_mul($bm_div(v, 100), amp), Math.sin($bm_mul($bm_mul($bm_mul(freq, t), 2), Math.PI))), Math.exp($bm_mul(decay, t))))) : value;\n    }\n} catch (err) {\n    $bm_rt = value = value;\n}"},"p":{"a":1,"k":[{"i":{"x":0.833,"y":0.833},"o":{"x":0.167,"y":0.167},"t":19.2,"s":[58.182,156.602,0],"to":[2.542,-1.042,0],"ti":[-2.542,1.042,0]},{"t":28.8,"s":[73.432,150.352,0]}],"ix":2},"a":{"a":0,"k":[124.156,138.64,0],"ix":1},"s":{"a":0,"k":[100,100,100],"ix":6}},"ao":0,"ef":[{"ty":5,"nm":"Excite - Rotation","np":8,"mn":"Pseudo/BNCA2506f0b33","ix":1,"en":1,"ef":[{"ty":7,"nm":"Enable","mn":"Pseudo/BNCA2506f0b33-0001","ix":1,"v":{"a":0,"k":1,"ix":1}},{"ty":6,"nm":"Properties","mn":"Pseudo/BNCA2506f0b33-0002","ix":2,"v":0},{"ty":0,"nm":"Overshoot","mn":"Pseudo/BNCA2506f0b33-0003","ix":3,"v":{"a":0,"k":5,"ix":3,"x":"var $bm_rt;\n$bm_rt = clamp(value, 0, 100);"}},{"ty":0,"nm":"Bounce","mn":"Pseudo/BNCA2506f0b33-0004","ix":4,"v":{"a":0,"k":30,"ix":4,"x":"var $bm_rt;\n$bm_rt = clamp(value, 0, 100);"}},{"ty":0,"nm":"Friction","mn":"Pseudo/BNCA2506f0b33-0005","ix":5,"v":{"a":0,"k":100,"ix":5,"x":"var $bm_rt;\n$bm_rt = clamp(value, 0, 100);"}},{"ty":6,"nm":"","mn":"Pseudo/BNCA2506f0b33-0006","ix":6,"v":0}]}],"shapes":[{"ty":"gr","it":[{"ind":0,"ty":"sh","ix":1,"ks":{"a":0,"k":{"i":[[-24.492,-28.634],[17.06,-14.043],[24.492,28.634],[-17.06,14.043]],"o":[[24.492,28.634],[-17.06,14.043],[-24.492,-28.634],[17.06,-14.044]],"v":[[30.889,-25.427],[44.346,51.847],[-30.889,25.428],[-44.346,-51.846]],"c":true},"ix":2},"nm":"Path 1","mn":"ADBE Vector Shape - Group","hd":false},{"ty":"st","c":{"a":0,"k":[0.019607843137,0.388235324037,0.392156892664,1],"ix":3},"o":{"a":0,"k":100,"ix":4},"w":{"a":0,"k":2,"ix":5},"lc":1,"lj":1,"ml":10,"bm":0,"nm":"Stroke 1","mn":"ADBE Vector Graphic - Stroke","hd":false},{"ty":"fl","c":{"a":0,"k":[0.776455269608,0.465318567613,0.254703028062,1],"ix":4},"o":{"a":0,"k":100,"ix":5},"r":1,"bm":0,"nm":"Fill 1","mn":"ADBE Vector Graphic - Fill","hd":false},{"ty":"tr","p":{"a":0,"k":[80.656,85.14],"ix":2},"a":{"a":0,"k":[0,0],"ix":1},"s":{"a":0,"k":[100,100],"ix":3},"r":{"a":0,"k":0,"ix":6},"o":{"a":0,"k":100,"ix":7},"sk":{"a":0,"k":0,"ix":4},"sa":{"a":0,"k":0,"ix":5},"nm":"Transform"}],"nm":"Group 1","np":3,"cix":2,"bm":0,"ix":1,"mn":"ADBE Vector Group","hd":false}],"ip":0,"op":487.2,"st":-220.8,"bm":0},{"ddd":0,"ind":2,"ty":4,"nm":"Layer 1 Outlines 2","sr":1,"ks":{"o":{"a":0,"k":100,"ix":11},"r":{"a":0,"k":0,"ix":10,"x":"var $bm_rt;\nvar enable, amp, freq, decay, n, t, v;\ntry {\n    $bm_rt = enable = effect('Excite - Rotation')('Pseudo/BNCA2506f0b33-0001');\n    if (enable == 0) {\n        $bm_rt = value;\n    } else {\n        amp = $bm_div(effect('Excite - Rotation')('Pseudo/BNCA2506f0b33-0003'), 2.5);\n        freq = $bm_div(effect('Excite - Rotation')('Pseudo/BNCA2506f0b33-0004'), 20);\n        decay = $bm_div(effect('Excite - Rotation')('Pseudo/BNCA2506f0b33-0005'), 20);\n        n = 0, 0 < numKeys && (n = nearestKey(time).index, key(n).time > time && n--), t = 0 === n ? 0 : $bm_sub(time, key(n).time), $bm_rt = 0 < n ? (v = velocityAtTime($bm_sub(key(n).time, $bm_div(thisComp.frameDuration, 10))), $bm_sum(value, $bm_div($bm_mul($bm_mul($bm_div(v, 100), amp), Math.sin($bm_mul($bm_mul($bm_mul(freq, t), 2), Math.PI))), Math.exp($bm_mul(decay, t))))) : value;\n    }\n} catch (err) {\n    $bm_rt = value = value;\n}"},"p":{"a":0,"k":[385.005,406.95,0],"ix":2},"a":{"a":0,"k":[60,155.25,0],"ix":1},"s":{"a":1,"k":[{"i":{"x":[0.833,0.833,0.833],"y":[0.833,0.833,0.833]},"o":{"x":[0.167,0.167,0.167],"y":[0.167,0.167,0.167]},"t":12,"s":[0,0,100]},{"t":21.6,"s":[180,180,100]}],"ix":6,"x":"var $bm_rt;\nvar enable, amp, freq, decay, n, t, v;\ntry {\n    $bm_rt = enable = effect('Excite - Scale')('Pseudo/BNCA2506f0b33-0001');\n    if (enable == 0) {\n        $bm_rt = value;\n    } else {\n        amp = $bm_div(effect('Excite - Scale')('Pseudo/BNCA2506f0b33-0003'), 2.5);\n        freq = $bm_div(effect('Excite - Scale')('Pseudo/BNCA2506f0b33-0004'), 20);\n        decay = $bm_div(effect('Excite - Scale')('Pseudo/BNCA2506f0b33-0005'), 20);\n        n = 0, 0 < numKeys && (n = nearestKey(time).index, key(n).time > time && n--), t = 0 === n ? 0 : $bm_sub(time, key(n).time), $bm_rt = 0 < n ? (v = velocityAtTime($bm_sub(key(n).time, $bm_div(thisComp.frameDuration, 10))), $bm_sum(value, $bm_div($bm_mul($bm_mul($bm_div(v, 100), amp), Math.sin($bm_mul($bm_mul($bm_mul(freq, t), 2), Math.PI))), Math.exp($bm_mul(decay, t))))) : value;\n    }\n} catch (err) {\n    $bm_rt = value = value;\n}"}},"ao":0,"ef":[{"ty":5,"nm":"Excite - Rotation","np":8,"mn":"Pseudo/BNCA2506f0b33","ix":1,"en":1,"ef":[{"ty":7,"nm":"Enable","mn":"Pseudo/BNCA2506f0b33-0001","ix":1,"v":{"a":0,"k":1,"ix":1}},{"ty":6,"nm":"Properties","mn":"Pseudo/BNCA2506f0b33-0002","ix":2,"v":0},{"ty":0,"nm":"Overshoot","mn":"Pseudo/BNCA2506f0b33-0003","ix":3,"v":{"a":0,"k":5,"ix":3,"x":"var $bm_rt;\n$bm_rt = clamp(value, 0, 100);"}},{"ty":0,"nm":"Bounce","mn":"Pseudo/BNCA2506f0b33-0004","ix":4,"v":{"a":0,"k":30,"ix":4,"x":"var $bm_rt;\n$bm_rt = clamp(value, 0, 100);"}},{"ty":0,"nm":"Friction","mn":"Pseudo/BNCA2506f0b33-0005","ix":5,"v":{"a":0,"k":100,"ix":5,"x":"var $bm_rt;\n$bm_rt = clamp(value, 0, 100);"}},{"ty":6,"nm":"","mn":"Pseudo/BNCA2506f0b33-0006","ix":6,"v":0}]},{"ty":5,"nm":"Excite - Scale","np":8,"mn":"Pseudo/BNCA2506f0b33","ix":2,"en":1,"ef":[{"ty":7,"nm":"Enable","mn":"Pseudo/BNCA2506f0b33-0001","ix":1,"v":{"a":0,"k":1,"ix":1}},{"ty":6,"nm":"Properties","mn":"Pseudo/BNCA2506f0b33-0002","ix":2,"v":0},{"ty":0,"nm":"Overshoot","mn":"Pseudo/BNCA2506f0b33-0003","ix":3,"v":{"a":0,"k":5,"ix":3,"x":"var $bm_rt;\n$bm_rt = clamp(value, 0, 100);"}},{"ty":0,"nm":"Bounce","mn":"Pseudo/BNCA2506f0b33-0004","ix":4,"v":{"a":0,"k":30,"ix":4,"x":"var $bm_rt;\n$bm_rt = clamp(value, 0, 100);"}},{"ty":0,"nm":"Friction","mn":"Pseudo/BNCA2506f0b33-0005","ix":5,"v":{"a":0,"k":100,"ix":5,"x":"var $bm_rt;\n$bm_rt = clamp(value, 0, 100);"}},{"ty":6,"nm":"","mn":"Pseudo/BNCA2506f0b33-0006","ix":6,"v":0}]}],"shapes":[{"ty":"gr","it":[{"ind":0,"ty":"sh","ix":1,"ks":{"a":0,"k":{"i":[[0,-37.379],[22.27,0],[0,37.379],[-22.27,0]],"o":[[0,37.379],[-22.271,0],[0,-37.379],[22.27,0]],"v":[[40.324,0],[0.001,67.681],[-40.324,0],[0.001,-67.681]],"c":true},"ix":2},"nm":"Path 1","mn":"ADBE Vector Shape - Group","hd":false},{"ty":"st","c":{"a":0,"k":[0.019607843137,0.388235324037,0.392156892664,1],"ix":3},"o":{"a":0,"k":100,"ix":4},"w":{"a":0,"k":2,"ix":5},"lc":1,"lj":1,"ml":10,"bm":0,"nm":"Stroke 1","mn":"ADBE Vector Graphic - Stroke","hd":false},{"ty":"fl","c":{"a":0,"k":[0.776455269608,0.465318567613,0.254703028062,1],"ix":4},"o":{"a":0,"k":100,"ix":5},"r":1,"bm":0,"nm":"Fill 1","mn":"ADBE Vector Graphic - Fill","hd":false},{"ty":"tr","p":{"a":0,"k":[59.573,86.931],"ix":2},"a":{"a":0,"k":[0,0],"ix":1},"s":{"a":0,"k":[100,100],"ix":3},"r":{"a":0,"k":0,"ix":6},"o":{"a":0,"k":100,"ix":7},"sk":{"a":0,"k":0,"ix":4},"sa":{"a":0,"k":0,"ix":5},"nm":"Transform"}],"nm":"Group 1","np":3,"cix":2,"bm":0,"ix":1,"mn":"ADBE Vector Group","hd":false}],"ip":0,"op":487.2,"st":-220.8,"bm":0}]}],"layers":[{"ddd":0,"ind":1,"ty":0,"nm":"LOGO LOADER - PRECOMP","refId":"comp_0","sr":1,"ks":{"o":{"a":0,"k":100,"ix":11},"r":{"a":0,"k":0,"ix":10},"p":{"a":0,"k":[48,38,0],"ix":2},"a":{"a":0,"k":[48,38,0],"ix":1},"s":{"a":0,"k":[100,100,100],"ix":6}},"ao":0,"w":96,"h":76,"ip":0,"op":78,"st":-42,"bm":0}],"markers":[]}